{
  "item_name": "VSS Vintorez",
  "key": "item.wpn.vss.name",
  "category": "weapon/sniper_rifle",
  "class": "Sniper Rifles",
  "stats": {
    "rank": "Master",
    "weight": 2.85,
    "other": [
      {
        "name": "Durability",
        "value": 100.0
      },
      {
        "name": "Max. durability",
        "value": 100.0
      },
      {
        "name": "Ammo type",
        "value": "9x39"
      },
      {
        "name": "Damage",
        "value": 41.0
      },
      {
        "name": "Clip capacity",
        "value": 20.0
      },
      {
        "name": "Maximum distance",
        "value": 170.0
      },
      {
        "name": "Rate of fire",
        "value": 600.0
      },
      {
        "name": "Reload",
        "value": 3.5
      },
      {
        "name": "Tactical reload",
        "value": 2.6
      },
      {
        "name": "Spread",
        "value": 0.209
      },
      {
        "name": "Hip-fire spread",
        "value": 3.75
      },
      {
        "name": "Vertical recoil",
        "value": 0.3
      },
      {
        "name": "Horizontal recoil",
        "value": 0.14
      },
      {
        "name": "Draw time",
        "value": 1.0
      },
      {
        "name": "Aiming time",
        "value": 0.25
      },
      {
        "name": "Stopping power",
        "value": 20.0
      },
      {
        "text": "Headshot damage: x1,5"
      }
    ]
  },
  "discription": "This 9 mm special sniper rifle (a VSS that was developed under the title Vintorez, a name that has remained in use) is a silenced sniper rifle. It was created in the Tochmash Central Scientific Research Institute for Precision Machine Engineering in Klimovsk at the start of the 1980s under the leadership of Pyotr Ivanovich Serdyukov. It was intended for use by special ops units."
}