{
  "item_name": "ATLAS Anabolic Steroid",
  "key": "item.med.atlas.name",
  "category": "medicine",
  "class": "Medicine",
  "stats": {
    "weight": 0.12,
    "other": [
      {
        "name": "Purpose",
        "value": "Stamina Improvement"
      },
      {
        "name": "Duration",
        "value": 300.0
      },
      {
        "name": "Poison",
        "value": 25.0
      },
      {
        "name": "Stamina",
        "value": 50.0
      },
      {
        "name": "Movement speed",
        "value": 2.0
      },
      {
        "name": "Carry weight",
        "value": 10.0
      },
      {
        "name": "Stamina regeneration",
        "value": 5.0
      }
    ]
  },
  "discription": "A foreign anabolic steroid with effects similar to other substances that are popular among stalkers like Hercules and Jiden. Due to the high dose of the active ingredient, usage of more than one of these substances at the same time is not recommended."
}