{
  "item_name": "Защитный костюм «Псарь»",
  "key": "item.arm.dogger.name",
  "category": "armor/combat",
  "class": "Боевые",
  "stats": {
    "rank": "Новичок",
    "weight": 8.0,
    "other": [
      {
        "name": "Прочность",
        "value": 100.0
      },
      {
        "name": "Макс. прочность",
        "value": 100.0
      },
      {
        "name": "Переносимый вес",
        "value": 5.0
      },
      {
        "name": "Пулестойкость",
        "value": 29.0
      },
      {
        "name": "Защита от разрыва",
        "value": 84.0
      },
      {
        "name": "Защита от взрыва",
        "value": 40.0
      },
      {
        "name": "Электрозащита",
        "value": 18.0
      },
      {
        "name": "Защита от огня",
        "value": 18.0
      },
      {
        "name": "Химзащита",
        "value": 18.0
      },
      {
        "name": "Защита от радиации",
        "value": 75.0
      },
      {
        "name": "Защита от биозаражения",
        "value": 75.0
      },
      {
        "name": "Защита от кровотечения",
        "value": 50.0
      }
    ]
  },
  "discription": "Костюм с хорошей защитой от мутантов. Особенно эффективен против мелких представителей - тушканов, кошек и собак, за что и получил своё название."
}