{
  "item_name": "Hive Container",
  "key": "item.cont.hive.name",
  "category": "containers",
  "class": "Backpacks and Containers",
  "stats": {
    "rank": "Master",
    "weight": 8.0,
    "other": [
      {
        "name": "Durability",
        "value": 100.0
      },
      {
        "name": "Max. durability",
        "value": 100.0
      },
      {
        "name": "Inner protection",
        "value": 80.0
      },
      {
        "name": "Effectiveness",
        "value": 80.0
      },
      {
        "name": "Capacity",
        "value": 5.0
      },
      {
        "name": "Movement speed",
        "value": -1.5
      }
    ]
  },
  "discription": "While the Bear’s Den was much more compact than the KZS bundle, it was still fairly cumbersome. Scientists conducted a series of projects to improve popular containers. This led to the Hive, a compact, spacious, reliable, but fairly expensive option."
}