{
  "id": "Rb1x",
  "name": "KZS-2",
  "key": "item.cont.kzs2.name",
  "category": "containers",
  "class": "Backpacks and Containers",
  "stats": {
    "rank": "Newbie",
    "weight": 3.5,
    "other": [
      {
        "name": "Durability",
        "value": 100.0
      },
      {
        "name": "Max. durability",
        "value": 100.0
      },
      {
        "name": "Inner protection",
        "value": 75.0
      },
      {
        "name": "Effectiveness",
        "value": 90.0
      },
      {
        "name": "Capacity",
        "value": 2.0
      }
    ]
  },
  "discription": "A set of two KZS-1 containers. Lets you carry two artifacts and, obviously, has good shielding capabilities."
}