{
  "item_name": "M1014",
  "key": "item.wpn.m1014.name",
  "category": "weapon/shotgun_rifle",
  "class": "Дробовики и ружья",
  "stats": {
    "rank": "Сталкер",
    "weight": 3.8000002,
    "other": [
      {
        "name": "Прочность",
        "value": 100.0
      },
      {
        "name": "Макс. прочность",
        "value": 100.0
      },
      {
        "name": "Тип боеприпасов",
        "value": "12 калибр"
      },
      {
        "name": "Урон",
        "value": 160.0
      },
      {
        "name": "Объем магазина",
        "value": 6.0
      },
      {
        "name": "Максимальная дистанция",
        "value": 55.0
      },
      {
        "name": "Скорострельность",
        "value": 200.0
      },
      {
        "name": "Перезарядка",
        "value": 4.5
      },
      {
        "name": "Разброс",
        "value": 3.57
      },
      {
        "name": "Разброс от бедра",
        "value": 4.5
      },
      {
        "name": "Вертикальная отдача",
        "value": 4.8
      },
      {
        "name": "Горизонтальная отдача",
        "value": 1.5
      },
      {
        "name": "Доставание",
        "value": 0.8
      },
      {
        "name": "Прицеливание",
        "value": 0.25
      },
      {
        "text": "Урон по мутантам: х1,5"
      }
    ]
  },
  "discription": "Benelli M4 Super 90, более известное как M1014 — гладкоствольное полуавтоматическое магазинное самозарядное ружьё, разработанное в Италии фирмой Benelli Armi S.p.A."
}