{
  "item_name": "Spiked Club",
  "key": "item.21041.name",
  "category": "weapon/melee",
  "class": "Melee Weapons",
  "stats": {
    "rank": "Stalker",
    "weight": 0.65,
    "other": [
      {
        "name": "Quick attack (min)",
        "value": 55.0
      },
      {
        "name": "Quick attack (max)",
        "value": 65.0
      },
      {
        "name": "Strong attack (min)",
        "value": 125.0
      },
      {
        "name": "Strong attack (max)",
        "value": 145.0
      },
      {
        "name": "Weapon reach (quick)",
        "value": 1.8
      },
      {
        "name": "Weapon reach (strong)",
        "value": 1.8
      },
      {
        "name": "Penetration",
        "value": 50.0
      },
      {
        "name": "Chance for a deep wound",
        "value": 30.0
      },
      {
        "text": "Backstab damage: x1,2"
      }
    ]
  },
  "discription": "A wooden club with bones, claws, and teeth from the undead on Boral."
}