{
  "item_name": "NR-43",
  "key": "item.21038.name",
  "category": "weapon/melee",
  "class": "Melee Weapons",
  "stats": {
    "rank": "Stalker",
    "weight": 0.15,
    "other": [
      {
        "name": "Quick attack (min)",
        "value": 40.0
      },
      {
        "name": "Quick attack (max)",
        "value": 50.0
      },
      {
        "name": "Strong attack (min)",
        "value": 100.0
      },
      {
        "name": "Strong attack (max)",
        "value": 120.0
      },
      {
        "name": "Weapon reach (quick)",
        "value": 1.8
      },
      {
        "name": "Weapon reach (strong)",
        "value": 1.9
      },
      {
        "name": "Penetration",
        "value": 40.0
      },
      {
        "name": "Chance for a deep wound",
        "value": 60.0
      },
      {
        "text": "Backstab damage: x1,2"
      }
    ]
  },
  "discription": "A combat knife in service with Soviet and Russian special security units since 1943."
}