{
  "id": "RyB7",
  "name": "Tanto with a Ring",
  "key": "item.21010.name",
  "category": "weapon/melee",
  "class": "Melee Weapons",
  "stats": {
    "rank": "Veteran",
    "weight": 0.22,
    "other": [
      {
        "name": "Quick attack (min)",
        "value": 40.0
      },
      {
        "name": "Quick attack (max)",
        "value": 50.0
      },
      {
        "name": "Strong attack (min)",
        "value": 100.0
      },
      {
        "name": "Strong attack (max)",
        "value": 120.0
      },
      {
        "name": "Weapon reach (quick)",
        "value": 1.7
      },
      {
        "name": "Weapon reach (strong)",
        "value": 1.8
      },
      {
        "name": "Penetration",
        "value": 60.0
      },
      {
        "name": "Chance for a deep wound",
        "value": 55.0
      },
      {
        "text": "Backstab damage: x1,3"
      }
    ]
  },
  "discription": "Although this knife vaguely resembles a karambit, it isn’t actually one. The length of the blade and its shape speak volumes about this weapon’s true nature."
}