{
  "item_name": "Colt Python",
  "key": "item.wpn.python.name",
  "category": "weapon/pistol",
  "class": "Пистолеты",
  "stats": {
    "rank": "Ветеран",
    "weight": 1.34,
    "other": [
      {
        "name": "Прочность",
        "value": 100.0
      },
      {
        "name": "Макс. прочность",
        "value": 100.0
      },
      {
        "name": "Тип боеприпасов",
        "value": "9 мм"
      },
      {
        "name": "Урон",
        "value": 76.0
      },
      {
        "name": "Объем магазина",
        "value": 6.0
      },
      {
        "name": "Максимальная дистанция",
        "value": 70.0
      },
      {
        "name": "Скорострельность",
        "value": 500.0
      },
      {
        "name": "Перезарядка",
        "value": 2.0
      },
      {
        "name": "Разброс",
        "value": 0.8
      },
      {
        "name": "Разброс от бедра",
        "value": 2.7
      },
      {
        "name": "Вертикальная отдача",
        "value": 0.9
      },
      {
        "name": "Горизонтальная отдача",
        "value": 0.6
      },
      {
        "name": "Доставание",
        "value": 0.4
      },
      {
        "name": "Прицеливание",
        "value": 0.2
      },
      {
        "text": "Урон увеличивается на 1,5% за каждый % отсутствующего здоровья цели, максимум +150% урона"
      }
    ]
  },
  "discription": "Шестизарядный револьвер калибра .357 Magnum. Револьвер собран на раме типа I, обладает плавным спуском и высокой точностью."
}