{
  "item_name": "СР-1 «Гюрза»",
  "key": "item.wpn.sr1.name",
  "category": "weapon/pistol",
  "class": "Пистолеты",
  "stats": {
    "rank": "Ветеран",
    "weight": 0.90000004,
    "other": [
      {
        "name": "Прочность",
        "value": 100.0
      },
      {
        "name": "Макс. прочность",
        "value": 100.0
      },
      {
        "name": "Тип боеприпасов",
        "value": "9 мм"
      },
      {
        "name": "Урон",
        "value": 59.0
      },
      {
        "name": "Объем магазина",
        "value": 18.0
      },
      {
        "name": "Максимальная дистанция",
        "value": 57.0
      },
      {
        "name": "Скорострельность",
        "value": 390.0
      },
      {
        "name": "Перезарядка",
        "value": 2.8
      },
      {
        "name": "Тактическая перезарядка",
        "value": 2.7
      },
      {
        "name": "Разброс",
        "value": 1.121
      },
      {
        "name": "Разброс от бедра",
        "value": 2.7
      },
      {
        "name": "Вертикальная отдача",
        "value": 0.35
      },
      {
        "name": "Горизонтальная отдача",
        "value": 0.25
      },
      {
        "name": "Доставание",
        "value": 0.45
      },
      {
        "name": "Прицеливание",
        "value": 0.25
      },
      {
        "text": "Урон увеличивается на 1% за каждый % отсутствующего здоровья цели, максимум +100% урона"
      }
    ]
  },
  "discription": "Самозарядный пистолет Сердюкова — пистолет, разработанный для силовых подразделений специального назначения, по программе НИОКР «Грач» под патрон повышенной эффективности."
}