{
  "id": "3Ze1",
  "name": "Тяжелый бронекостюм «Туманный охотник»",
  "key": "item.arm.smog.name",
  "category": "armor/combat",
  "class": "Боевые",
  "stats": {
    "rank": "Ветеран",
    "weight": 14.0,
    "other": [
      {
        "name": "Прочность",
        "value": 100.0
      },
      {
        "name": "Макс. прочность",
        "value": 100.0
      },
      {
        "name": "Выносливость",
        "value": -20.0
      },
      {
        "name": "Скорость передвижения",
        "value": -2.0
      },
      {
        "name": "Переносимый вес",
        "value": 4.0
      },
      {
        "text": "Прибор ночного видения"
      },
      {
        "name": "Пулестойкость",
        "value": 124.0
      },
      {
        "name": "Защита от разрыва",
        "value": 133.0
      },
      {
        "name": "Защита от взрыва",
        "value": 190.0
      },
      {
        "name": "Электрозащита",
        "value": 127.0
      },
      {
        "name": "Защита от огня",
        "value": 127.0
      },
      {
        "name": "Химзащита",
        "value": 127.0
      },
      {
        "name": "Защита от радиации",
        "value": 200.0
      },
      {
        "name": "Защита от температуры",
        "value": 60.0
      },
      {
        "name": "Защита от биозаражения",
        "value": 200.0
      },
      {
        "name": "Защита от пси-излучения",
        "value": 135.0
      },
      {
        "name": "Защита от кровотечения",
        "value": 64.0
      }
    ]
  },
  "discription": "Неизвестный мастер, создавший «Зарю», подарил нам эту модифицикацию «Восхода». Кислородные баллоны, хороший разгрузочный жилет, улучшенная броня, новейший ПНВ."
}